ocean/__init__.py
ocean/abc/__init__.py
ocean/abc/_mapper.py
ocean/cp/__init__.py
ocean/cp/_base.py
ocean/cp/_env.py
ocean/cp/_explainer.py
ocean/cp/_explanation.py
ocean/cp/_model.py
ocean/cp/_builder/__init__.py
ocean/cp/_builder/model.py
ocean/cp/_managers/__init__.py
ocean/cp/_managers/_feature.py
ocean/cp/_managers/_garbage.py
ocean/cp/_managers/_tree.py
ocean/cp/_variables/__init__.py
ocean/cp/_variables/_feature.py
ocean/cp/_variables/_tree.py
ocean/datasets/__init__.py
ocean/datasets/_load.py
ocean/feature/__init__.py
ocean/feature/_feature.py
ocean/feature/_keeper.py
ocean/feature/_parse.py
ocean/maxsat/__init__.py
ocean/maxsat/_base.py
ocean/maxsat/_explainer.py
ocean/maxsat/_explanation.py
ocean/maxsat/_model.py
ocean/maxsat/_solver.py
ocean/maxsat/_builder/__init__.py
ocean/maxsat/_builder/model.py
ocean/maxsat/_managers/__init__.py
ocean/maxsat/_managers/_feature.py
ocean/maxsat/_managers/_garbage.py
ocean/maxsat/_managers/_tree.py
ocean/maxsat/_variables/__init__.py
ocean/maxsat/_variables/_feature.py
ocean/maxsat/_variables/_tree.py
ocean/mip/__init__.py
ocean/mip/_base.py
ocean/mip/_explainer.py
ocean/mip/_explanation.py
ocean/mip/_model.py
ocean/mip/_typing.py
ocean/mip/_builders/__init__.py
ocean/mip/_builders/flow.py
ocean/mip/_builders/model.py
ocean/mip/_managers/__init__.py
ocean/mip/_managers/_feature.py
ocean/mip/_managers/_garbage.py
ocean/mip/_managers/_tree.py
ocean/mip/_variables/__init__.py
ocean/mip/_variables/_feature.py
ocean/mip/_variables/_tree.py
ocean/tree/__init__.py
ocean/tree/_keeper.py
ocean/tree/_node.py
ocean/tree/_node.pyi
ocean/tree/_parse.py
ocean/tree/_parse_xgb.py
ocean/tree/_protocol.py
ocean/tree/_tree.py
ocean/tree/_utils.py
ocean/typing/__init__.py
oceanpy-2.0.2.dist-info/licenses/LICENSE
oceanpy-2.0.2.dist-info/METADATA
oceanpy-2.0.2.dist-info/WHEEL
oceanpy-2.0.2.dist-info/top_level.txt
oceanpy-2.0.2.dist-info/RECORD
