Metadata-Version: 2.4
Name: oceanpy
Version: 2.0.2
Summary: A simple Python package Optimal Counterfactual Explanations in Tree Ensembles
Author-email: Youssouf Emine <youssouf.emine@polymtl.ca>, Awa Khouna <awa.khouna@polymtl.ca>, Julien Ferry <julien.ferry@polymtl.ca>, Thibaut Vidal <thibaut.vidal@polymtl.ca>, Alexandre Forel <alexandre.forel@polymtl.ca>
License: MIT License
Project-URL: Homepage, https://github.com/vidalt/OCEAN
Project-URL: Repository, https://github.com/vidalt/OCEAN
Project-URL: Issues, https://github.com/vidalt/OCEAN/issues
Classifier: Development Status :: 4 - Beta
Classifier: Intended Audience :: Developers
Classifier: License :: OSI Approved :: MIT License
Classifier: Topic :: Software Development :: Libraries
Classifier: Programming Language :: Python :: 3
Classifier: Programming Language :: Python :: 3.12
Classifier: Programming Language :: Python :: 3.13
Classifier: Programming Language :: Python :: 3 :: Only
Requires-Python: >=3.12
License-File: LICENSE
Requires-Dist: anytree
Requires-Dist: gurobipy
Requires-Dist: numpy
Requires-Dist: ortools>=9.12
Requires-Dist: pandas
Requires-Dist: pydantic
Requires-Dist: scikit-learn
Requires-Dist: xgboost
Requires-Dist: python-sat
Provides-Extra: dev
Requires-Dist: coverage; extra == "dev"
Requires-Dist: mypy; extra == "dev"
Requires-Dist: pandas-stubs; extra == "dev"
Requires-Dist: pyright; extra == "dev"
Requires-Dist: pytest; extra == "dev"
Requires-Dist: pytest-cov; extra == "dev"
Requires-Dist: ruff; extra == "dev"
Requires-Dist: scipy-stubs; extra == "dev"
Requires-Dist: tox; extra == "dev"
Provides-Extra: test
Requires-Dist: coverage; extra == "test"
Requires-Dist: mypy; extra == "test"
Requires-Dist: pandas-stubs; extra == "test"
Requires-Dist: pyright; extra == "test"
Requires-Dist: pytest; extra == "test"
Requires-Dist: pytest-cov; extra == "test"
Requires-Dist: ruff; extra == "test"
Requires-Dist: scipy-stubs; extra == "test"
Requires-Dist: tox; extra == "test"
Provides-Extra: example
Requires-Dist: rich; extra == "example"
Requires-Dist: matplotlib; extra == "example"
Dynamic: license-file
